pymodulegen/__init__.py
pymodulegen/__main__.py
pymodulegen-0.0.8.dist-info/LICENSE
pymodulegen-0.0.8.dist-info/METADATA
pymodulegen-0.0.8.dist-info/WHEEL
pymodulegen-0.0.8.dist-info/entry_points.txt
pymodulegen-0.0.8.dist-info/top_level.txt
pymodulegen-0.0.8.dist-info/RECORD
