Metadata-Version: 2.1
Name: pymodulegen
Version: 0.0.8
Summary: Generate module and __init__.py (in case of package) files in the specified directory. Set root directory and add root directory path to sys path so that absolute path imports will work even in child modules.
Author-email: Narendran A I <narenkrithick@gmail.com>
Project-URL: Homepage, https://github.com/YashNarK/pymodulegen
Project-URL: Bug Tracker, https://github.com/YashNarK/pymodulegen/issues
Classifier: Programming Language :: Python :: 3
Classifier: License :: OSI Approved :: MIT License
Classifier: Operating System :: OS Independent
Requires-Python: >=3.7
License-File: LICENSE
